ringspy/MeshGenTools.py
ringspy/__init__.py
ringspy/py.typed
ringspy-1.0.2.dist-info/LICENSE
ringspy-1.0.2.dist-info/METADATA
ringspy-1.0.2.dist-info/WHEEL
ringspy-1.0.2.dist-info/top_level.txt
ringspy-1.0.2.dist-info/RECORD
